KannadaImage2Text/__init__.py
KannadaImage2Text/main.py
KannadaImage2Text/utils.py
kannadaimage2text-0.0.1.dist-info/METADATA
kannadaimage2text-0.0.1.dist-info/WHEEL
kannadaimage2text-0.0.1.dist-info/licenses/LICENSE.txt
kannadaimage2text-0.0.1.dist-info/RECORD
