Metadata-Version: 2.4
Name: KannadaImage2Text
Version: 0.0.1
Summary: A Kannada Image to text package
Project-URL: Homepage, https://github.com/pypa/KannadaImage2Text
Project-URL: Issues, https://github.com/pypa/KannadaImage2Text/issues
Author-email: Aisiri Patil <patil.aisiri@google.com>
License-Expression: MIT
License-File: LICENSE.txt
Classifier: Operating System :: OS Independent
Classifier: Programming Language :: Python :: 3
Requires-Python: >=3.9
